watchftp/__init__.py
watchftp/events.py
watchftp/index.py
watchftp/logging.py
watchftp/metrics.py
watchftp/patterns.py
watchftp/redis.py
watchftp/scheduler.py
watchftp/settings.py
watchftp/types.py
watchftp/version.py
watchftp/watcher.py
watchftp/connectors/__init__.py
watchftp/connectors/base.py
watchftp/connectors/ftp.py
watchftp/connectors/sftp.py
watchftp-0.0.1.dist-info/licenses/LICENSE
watchftp-0.0.1.dist-info/METADATA
watchftp-0.0.1.dist-info/WHEEL
watchftp-0.0.1.dist-info/top_level.txt
watchftp-0.0.1.dist-info/RECORD
