Metadata-Version: 2.4
Name: watchftp
Version: 0.0.1
Summary: Simple, modern and fast FTP watching
Author-email: Tri Songz <ts@sgz.ai>
Requires-Python: >=3.12
License-File: LICENSE
Requires-Dist: pydantic>=2.4
Requires-Dist: pydantic-settings>=2.1
Requires-Dist: aioftp>=0.27
Requires-Dist: asyncssh>=2.14
Requires-Dist: redis[hiredis]>=5.0
Requires-Dist: wcmatch>=9.0
Requires-Dist: prometheus-client>=0.20
Requires-Dist: mkdocs-material>=9.7.0
Requires-Dist: mkdocs>=1.6.1
Provides-Extra: dev
Requires-Dist: pytest>=8.4; extra == "dev"
Requires-Dist: pytest-asyncio>=1.2; extra == "dev"
Requires-Dist: pyftpdlib>=2.1; extra == "dev"
Dynamic: license-file
